fivemisrael/__init__.py
fivemisrael/client.py
fivemisrael-1.0.3.dist-info/licenses/LICENSE
fivemisrael-1.0.3.dist-info/METADATA
fivemisrael-1.0.3.dist-info/WHEEL
fivemisrael-1.0.3.dist-info/top_level.txt
fivemisrael-1.0.3.dist-info/RECORD
